fathom_lib/__init__.py
fathom_lib/pandas_utils.py
fathom_lib/pipeline_data.py
fathom_lib/pipeline_runner.py
fathom_lib/utils.py
fathom_lib/workflow.py
fathom_lib/component_autogeneration/__init__.py
fathom_lib/component_autogeneration/rest_html.py
fathom_lib/component_autogeneration/submodules.py
fathom_lib/component_autogeneration/distpy/__init__.py
fathom_lib/component_autogeneration/distpy/generate_components.py
fathom_lib/component_autogeneration/sklearn/__init__.py
fathom_lib/component_autogeneration/sklearn/extract_all_sklearn_vuetify_schema_form.py
fathom_lib/component_autogeneration/sklearn/generate_ui_components.py
fathom_lib/component_autogeneration/sklearn/human_modules_preparation.py
fathom_lib/component_autogeneration/sklearn/test_extract.py
fathom_lib/data_analysis/__init__.py
fathom_lib/data_analysis/dataframe_simple_eda.py
fathom_lib/datasources/__init__.py
fathom_lib/datasources/download.py
fathom_lib/endpoints/__init__.py
fathom_lib/endpoints/app.py
fathom_lib/experimentation/__init__.py
fathom_lib/experimentation/loggers.py
fathom_lib/experimentation/model_handler.py
fathom_lib/metrics/__init__.py
fathom_lib/metrics/aft_accuracy.py
fathom_lib/metrics/aft_concordance_index.py
fathom_lib/metrics/shap_feature_importance.py
fathom_lib/metrics/sklearn_metrics.py
fathom_lib/models/__init__.py
fathom_lib/models/autokeras_models.py
fathom_lib/models/xgboost_aft.py
fathom_lib/report/__init__.py
fathom_lib/report/classification_report_template.html
fathom_lib/report/template_inputs.py
fathom_lib/runnable/__init__.py
fathom_lib/runnable/components.py
fathom_lib/runnable/expanding_window.py
fathom_lib/runnable/single_split.py
fathom_lib/transformers/__init__.py
fathom_lib/transformers/pandasify.py
fathom_lib/transformers/range_cleaner.py
fathom_lib/transformers/rolling_aggregation.py
fathom_lib/transformers/row_sampler.py
fathom_lib/transformers/sparkify.py
fathom_lib/validation/__init__.py
fathom_lib/validation/validation.py
fathom_lib-0.1.9.dist-info/METADATA
fathom_lib-0.1.9.dist-info/WHEEL
fathom_lib-0.1.9.dist-info/dependency_links.txt
fathom_lib-0.1.9.dist-info/top_level.txt
fathom_lib-0.1.9.dist-info/RECORD
